Metadata-Version: 1.0
Name: xmemx
Version: 0.0.2
Summary: xmemx.
Home-page: http://xmemx.com
Author: i@xlzd.me
Author-email: UNKNOWN
License: GPLv3
Platform: UNKNOWN
